cronos_chain_client/__init__.py
cronos_chain_client/client.py
cronos_chain_client/tokens/__init__.py
cronos_chain_client/tokens/tokens.py
cronos_chain_client/tokens/__pycache__/__init__.cpython-312.pyc
cronos_chain_client/tokens/__pycache__/tokens.cpython-312.pyc
cronos_chain_client/tokens/mainnet/evm_token_list.json
cronos_chain_client-0.1.5.dist-info/METADATA
cronos_chain_client-0.1.5.dist-info/WHEEL
cronos_chain_client-0.1.5.dist-info/top_level.txt
cronos_chain_client-0.1.5.dist-info/RECORD
