Metadata-Version: 2.1
Name: cronos_chain_client
Version: 0.1.5
Summary: A Python client for interacting with the Cronos Chains
Home-page: https://github.com/cronos-labs/cronos-chain-client/tree/main/py
Author: rarcifa
Author-email: rarcifa <rarcifa@gmail.com>
License: MIT
Classifier: Programming Language :: Python :: 3
Classifier: License :: OSI Approved :: MIT License
Classifier: Operating System :: OS Independent
Requires-Python: >=3.6
